bearcheck/__init__.py
bearcheck/check.py
bearcheck/py.typed
bearcheck-0.1.4.dist-info/WHEEL
bearcheck-0.1.4.dist-info/METADATA
bearcheck-0.1.4.dist-info/RECORD
