Metadata-Version: 2.4
Name: bearcheck
Version: 0.1.4
Summary: Tiny beartype helper lib for inline type assertion and narrowing (not affiliated)
Author: Louis Burda
Author-email: Louis Burda <dev@sinitax.com>
License-Expression: MIT
Requires-Dist: beartype>=0.22.5
Requires-Python: >=3.10
